lyra_geometry/__init__.py
lyra_geometry/core.py
lyra_geometry/diff_ops.py
lyra_geometry/invariants.py
lyra_geometry/tensors.py
lyra_geometry/utils.py
lyra_geometry-0.1.20.dist-info/licenses/LICENSE
lyra_geometry-0.1.20.dist-info/METADATA
lyra_geometry-0.1.20.dist-info/WHEEL
lyra_geometry-0.1.20.dist-info/top_level.txt
lyra_geometry-0.1.20.dist-info/RECORD
