Metadata-Version: 2.4
Name: lyra-geometry
Version: 0.1.20
Summary: Python library for symbolic differential geometry: tensors, connections, and curvature.
Author: Eduardo
License: MIT License
Classifier: Programming Language :: Python :: 3
Classifier: License :: OSI Approved :: MIT License
Classifier: Operating System :: OS Independent
Requires-Python: >=3.9
License-File: LICENSE
Requires-Dist: sympy>=1.12
Provides-Extra: dev
Requires-Dist: pytest; extra == "dev"
Dynamic: license-file
